filters/__init__.py
filters/aliases.py
filters/base.py
filters/complex.py
filters/extensions.py
filters/handlers.py
filters/macros.py
filters/number.py
filters/simple.py
filters/string.py
filters/test.py
phx_filters-3.4.0.dist-info/LICENCE.txt
phx_filters-3.4.0.dist-info/METADATA
phx_filters-3.4.0.dist-info/WHEEL
phx_filters-3.4.0.dist-info/top_level.txt
phx_filters-3.4.0.dist-info/RECORD
