Metadata-Version: 2.1
Name: phx-filters
Version: 3.4.0
Summary: Validation and data pipelines made easy!
Author-email: Phoenix Zerin <phx@phx.nz>
License: MIT License
Project-URL: Documentation, https://filters.readthedocs.io/
Project-URL: Changelog, https://github.com/todofixthis/filters/releases
Project-URL: Issues, https://github.com/todofixthis/filters/issues
Project-URL: Repository, https://github.com/todofixthis/filters
Keywords: data processing,pipeline,transformation,validation
Classifier: Development Status :: 5 - Production/Stable
Classifier: Intended Audience :: Developers
Classifier: License :: OSI Approved :: MIT License
Classifier: Programming Language :: Python :: 3
Classifier: Programming Language :: Python :: 3.12
Classifier: Programming Language :: Python :: 3.11
Classifier: Programming Language :: Python :: 3.10
Classifier: Programming Language :: Python :: Implementation :: PyPy
Classifier: Topic :: Software Development :: Libraries :: Python Modules
Classifier: Topic :: Text Processing :: Filters
Requires-Python: >=3.10
License-File: LICENCE.txt
Requires-Dist: phx-class-registry >=4.1.0
Requires-Dist: python-dateutil
Requires-Dist: pytz
Requires-Dist: regex >=2018.8.17
Provides-Extra: build-system
Requires-Dist: build ; extra == 'build-system'
Requires-Dist: twine ; extra == 'build-system'
Provides-Extra: django
Requires-Dist: phx-filters-django ; extra == 'django'
Provides-Extra: docs-builder
Requires-Dist: sphinx ; extra == 'docs-builder'
Requires-Dist: sphinx-rtd-theme ; extra == 'docs-builder'
Provides-Extra: iso
Requires-Dist: phx-filters-iso ; extra == 'iso'
Provides-Extra: test-runner
Requires-Dist: tox ; extra == 'test-runner'
